cowlist.py
cowlist-0.1.0a5.dist-info/licenses/LICENSE
cowlist-0.1.0a5.dist-info/METADATA
cowlist-0.1.0a5.dist-info/WHEEL
cowlist-0.1.0a5.dist-info/top_level.txt
cowlist-0.1.0a5.dist-info/RECORD
