Metadata-Version: 2.4
Name: cowlist
Version: 0.1.0a5
Summary: An efficient, immutable, type-safe copy-on-write (COW) list implementation for Python 2+.
Author-email: Jifeng Wu <jifengwu2k@gmail.com>
License-Expression: Apache-2.0
Project-URL: Homepage, https://github.com/jifengwu2k/cowlist
Project-URL: Bug Tracker, https://github.com/jifengwu2k/cowlist/issues
Classifier: Programming Language :: Python :: 2
Classifier: Programming Language :: Python :: 3
Classifier: Operating System :: OS Independent
Requires-Python: >=2
License-File: LICENSE
Requires-Dist: canonical-range
Requires-Dist: determine-slice-assignment-action
Requires-Dist: tuplehash
Requires-Dist: typing; python_version < "3.5"
Dynamic: license-file
